{
  "cations": {
    "ag+": {
      "symbol": "Ag⁺",
      "name": "Silver",
      "inherent_color": "colorless",
      "flame_color": null
    },
    "ba2+": {
      "symbol": "Ba²⁺",
      "name": "Barium",
      "inherent_color": "colorless",
      "flame_color": "yellow-green"
    },
    "ca2+": {
      "symbol": "Ca²⁺",
      "name": "Calcium",
      "inherent_color": "colorless",
      "flame_color": "brick-red"
    },
    "cu2+": {
      "symbol": "Cu²⁺",
      "name": "Copper(II)",
      "inherent_color": "light-blue",
      "flame_color": "blue-green"
    },
    "fe2+": {
      "symbol": "Fe²⁺",
      "name": "Iron(II)",
      "inherent_color": "light-green",
      "flame_color": null
    },
    "fe3+": {
      "symbol": "Fe³⁺",
      "name": "Iron(III)",
      "inherent_color": "orange",
      "flame_color": null
    },
    "k+": {
      "symbol": "K⁺",
      "name": "Potassium",
      "inherent_color": "colorless",
      "flame_color": "pale-violet"
    },
    "li+": {
      "symbol": "Li⁺",
      "name": "Lithium",
      "inherent_color": "colorless",
      "flame_color": "carmine-red"
    },
    "na+": {
      "symbol": "Na⁺",
      "name": "Sodium",
      "inherent_color": "colorless",
      "flame_color": "yellow"
    },
    "nh4+": {
      "symbol": "NH₄⁺",
      "name": "Ammonium",
      "inherent_color": "colorless",
      "flame_color": null
    },
    "ni2+": {
      "symbol": "Ni²⁺",
      "name": "Nickel(II)",
      "inherent_color": "light-green",
      "flame_color": null
    },
    "al3+": {
      "symbol": "Al³⁺",
      "name": "Aluminum",
      "inherent_color": "colorless",
      "flame_color": null
    },
    "bi3+": {
      "symbol": "Bi³⁺",
      "name": "Bismuth(III)",
      "inherent_color": "colorless",
      "flame_color": null
    },
    "pb2+": {
      "symbol": "Pb²⁺",
      "name": "Lead(II)",
      "inherent_color": "colorless",
      "flame_color": null
    },
    "sr2+": {
      "symbol": "Sr²⁺",
      "name": "Strontium",
      "inherent_color": "colorless",
      "flame_color": "red"
    },
    "co2+": {
      "symbol": "Co²⁺",
      "name": "Cobalt(II)",
      "inherent_color": "pink",
      "flame_color": null
    },
    "cr3+": {
      "symbol": "Cr³⁺",
      "name": "Chromium(III)",
      "inherent_color": "green",
      "flame_color": null
    },
    "mg2+": {
      "symbol": "Mg²⁺",
      "name": "Magnesium",
      "inherent_color": "colorless",
      "flame_color": null
    },
    "mn2+": {
      "symbol": "Mn²⁺",
      "name": "Manganese(II)",
      "inherent_color": "pale-pink",
      "flame_color": null
    },
    "zn2+": {
      "symbol": "Zn²⁺",
      "name": "Zinc",
      "inherent_color": "colorless",
      "flame_color": null
    },
    "hg2+": {
      "symbol": "Hg²⁺",
      "name": "Mercury(II)",
      "inherent_color": "colorless",
      "flame_color": null
    },
    "cd2+": {
      "symbol": "Cd²⁺",
      "name": "Cadmium",
      "inherent_color": "colorless",
      "flame_color": null
    },
    "sn2+": {
      "symbol": "Sn²⁺",
      "name": "Tin(II)",
      "inherent_color": "colorless",
      "flame_color": null
    },
    "h+": {
      "symbol": "H⁺",
      "name": "Acid",
      "inherent_color": "colorless",
      "flame_color": null
    }
  },
  "special_ions": {
    "mno4-": {
      "symbol": "MnO₄⁻",
      "name": "Permanganate",
      "inherent_color": "purple",
      "type": "anion"
    },
    "oh-": {
      "symbol": "OH⁻",
      "name": "Hydroxide",
      "inherent_color": "colorless",
      "type": "anion"
    }
  }
}
